useful_fields/__init__.py
useful_fields/fields.py
django_useful_fields-0.0.5.dist-info/LICENSE
django_useful_fields-0.0.5.dist-info/METADATA
django_useful_fields-0.0.5.dist-info/WHEEL
django_useful_fields-0.0.5.dist-info/top_level.txt
django_useful_fields-0.0.5.dist-info/RECORD
