Metadata-Version: 2.1
Name: django-useful-fields
Version: 0.0.5
Summary: Some useful database field definitions for Django.
Home-page: https://github.com/rmecham/django-useful-fields/
Author: Rob Mecham
License: MIT
Classifier: Development Status :: 3 - Alpha
Classifier: Environment :: Web Environment
Classifier: Framework :: Django
Classifier: Intended Audience :: Developers
Classifier: License :: OSI Approved :: MIT License
Classifier: Operating System :: OS Independent
Classifier: Programming Language :: Python :: 3.6
Classifier: Programming Language :: Python :: 3.7
Classifier: Programming Language :: Python :: 3.8
Classifier: Programming Language :: Python :: 3.9
Classifier: Programming Language :: Python :: 3.10
Classifier: Programming Language :: Python :: 3
Classifier: Programming Language :: Python
Classifier: Topic :: Internet :: WWW/HTTP
Classifier: Topic :: Software Development :: Libraries :: Python Modules
License-File: LICENSE
Requires-Dist: Django (>=3.0)
Requires-Dist: bleach (>=1.4)
Requires-Dist: Markdown (>=2.6)
Requires-Dist: pytz (>=2015)
